datacenter/__init__.py
datacenter/app_space.py
datacenter/cli.py
datacenter/datacenter.py
datacenter/dataset.py
datacenter/exceptions.py
datacenter/tools.py
datacenter/biology/__init__.py
datacenter/biology/molecule.py
datacenter/biology/target.py
datacenter/internals/__init__.py
datacenter/internals/downloader.py
datacenter/internals/transfer.py
datacenter/internals/uploader.py
datacenter-0.0.2.dist-info/AUTHORS.rst
datacenter-0.0.2.dist-info/METADATA
datacenter-0.0.2.dist-info/WHEEL
datacenter-0.0.2.dist-info/entry_points.txt
datacenter-0.0.2.dist-info/top_level.txt
datacenter-0.0.2.dist-info/RECORD
