Metadata-Version: 2.1
Name: datacenter
Version: 0.0.2
Summary: datacenter-sdk and datacenter-cli for DataCenter@XARC
Home-page: https://bitbucket.org/wangxinyong-xtalpi/datacenter
Author: Tacey Wong
Author-email: xinyong.wang@xtalpi.com
License: UNKNOWN
Keywords: datacenter
Platform: UNKNOWN
Classifier: Development Status :: 2 - Pre-Alpha
Classifier: Intended Audience :: Developers
Classifier: Natural Language :: English
Classifier: Programming Language :: Python :: 3
Classifier: Programming Language :: Python :: 3.6
Classifier: Programming Language :: Python :: 3.7
Classifier: Programming Language :: Python :: 3.8
Requires-Python: >=3.5
Requires-Dist: click (>=7.0.0)
Requires-Dist: requests (>2.0.0)
Requires-Dist: python-jose[pycryptodome] (==3.1.0)
